Constantine/__init__.py
Constantine/__main__.py
Constantine/auto_poster.py
Constantine/main.py
Constantine/utils.py
Constantine-1.1.3.data/data/Constantine/latex_template.txt
Constantine-1.1.3.data/data/Constantine/settings.json
Constantine-1.1.3.data/data/Constantine/special_text.txt
Constantine-1.1.3.data/data/Constantine/tex/logo/default-logo.png
Constantine-1.1.3.dist-info/DESCRIPTION.rst
Constantine-1.1.3.dist-info/METADATA
Constantine-1.1.3.dist-info/RECORD
Constantine-1.1.3.dist-info/WHEEL
Constantine-1.1.3.dist-info/entry_points.txt
Constantine-1.1.3.dist-info/metadata.json
Constantine-1.1.3.dist-info/top_level.txt
