Metadata-Version: 2.0
Name: Constantine
Version: 1.1.3
Summary: Automatic event poster generator
Home-page: https://github.com/icydoge/Constantine
Author: C Shi
Author-email: icydoge@gmail.com
License: MIT
Keywords: pdf generator
Platform: UNKNOWN
Classifier: Development Status :: 4 - Beta
Classifier: Intended Audience :: End Users/Desktop
Classifier: Topic :: Text Processing :: General
Classifier: License :: OSI Approved :: MIT License
Classifier: Programming Language :: Python :: 3.3
Classifier: Programming Language :: Python :: 3.4
Classifier: Programming Language :: Python :: 3.5
Classifier: Programming Language :: Python :: 3.6
Requires-Dist: requests
